MANIFEST.in
README.txt
op5-cli
setup.py
man/op5-cli.1
op5_cli.egg-info/PKG-INFO
op5_cli.egg-info/SOURCES.txt
op5_cli.egg-info/dependency_links.txt
op5_cli.egg-info/requires.txt
op5_cli.egg-info/top_level.txt
op5lib/.gitignore
op5lib/CHANGELOG.md
op5lib/README.md
op5lib/__init__.py
op5lib/__init__.pyc
op5lib/op5.py
op5lib/op5.pyc
op5lib/requirements.txt
op5lib/setup.py
op5lib/setup.pyc
t/01-basic.bash