Metadata-Version: 1.0
Name: op5-cli
Version: 1.0.2
Summary: A command-line interface for the OP5 monitoring system
Home-page: https://github.com/ozans/op5-cli
Author: Ozan Safi
Author-email: ozansafi@gmail.com
License: LICENSE.txt
Platform: UNKNOWN
